webcopy/__init__.py
webcopy/webcopy.py
webcopy-1.0.1.dist-info/LICENSE
webcopy-1.0.1.dist-info/METADATA
webcopy-1.0.1.dist-info/WHEEL
webcopy-1.0.1.dist-info/entry_points.txt
webcopy-1.0.1.dist-info/top_level.txt
webcopy-1.0.1.dist-info/zip-safe
webcopy-1.0.1.dist-info/RECORD
