Metadata-Version: 2.1
Name: webcopy
Version: 1.0.1
Summary: tools for copy web
Home-page: https://github.com/dzxs/webcopy
Author: d2x3
Author-email: d2x3@outlook.com
License: UNKNOWN
Keywords: webcopy
Platform: UNKNOWN
Classifier: Programming Language :: Python :: 3 :: Only
Classifier: Programming Language :: Python :: 3.6
Classifier: Programming Language :: Python :: 3.7
Classifier: Programming Language :: Python :: 3.8
Classifier: Programming Language :: Python :: Implementation :: CPython
Classifier: License :: OSI Approved :: MIT License
Classifier: Operating System :: MacOS
Classifier: Operating System :: POSIX
Classifier: Operating System :: Microsoft :: Windows
Requires-Python: >=3
Requires-Dist: mitmproxy (>=5.0.0)
